{
  "date": "2026-05-23",
  "BAD01": {
    "readings": [
      2.65,
      2.66,
      2.66,
      2.57,
      2.51,
      2.39,
      2.3,
      2.21
    ],
    "rainfall_readings": [
      0.0,
      1.1,
      0.0,
      0.0,
      0.0,
      0.0,
      0.0,
      0.0
    ],
    "w_avg": 2.4938,
    "w_max": 2.66,
    "w_min": 2.21,
    "rainfall_mm": 6.4,
    "rising_flag": 0
  },
  "THA01": {
    "readings": [
      2.51,
      2.51,
      2.4,
      2.03,
      1.99,
      1.95,
      1.94,
      1.88
    ],
    "rainfall_readings": [
      0.0,
      0.0,
      0.0,
      0.0,
      0.0,
      0.0,
      0.0,
      0.0
    ],
    "w_avg": 2.1512,
    "w_max": 2.51,
    "w_min": 1.88,
    "rainfall_mm": 0.0,
    "rising_flag": 0
  }
}